uart_verify/uart_rx.v
module receiver#(parameter integer clock = 30000000, baudrate = 115200)
(input clk,
input rst,
input rx,
input parity_en,
input parity_type,
output reg [7:0] rx_data,
output reg rx_valid,
output reg rx_error
);

localparam integer t_bit = clock/baudrate;
localparam integer half_bit = t_bit/2;


reg [2:0] state,next;
reg [12:0] baudcount;
reg [2:0] bitcount;
reg [7:0] shift_reg;
reg parity;
reg parity_error;

parameter rx_idle = 3'd0,rx_start_check = 3'd5,rx__data = 3'd2,rx_parity = 3'd3,rx_stop = 3'd4;

always@(posedge clk or posedge rst) begin
	if(rst)
		state <= rx_idle;
	else 
		state <= next;
	end

always@(posedge clk or posedge rst) begin
	if(rst) begin
		baudcount <= 0;
		bitcount <= 0;
	end
	else if(state == rx_idle)begin
			baudcount <= 0;
			bitcount <= 0;
	end
	else if(state == rx_start_check)begin
		if(baudcount == half_bit-1) begin
			baudcount <= 0;
		end
		else
			baudcount <= baudcount +1;
			
	end
	else begin
		if(baudcount == t_bit-1)begin
			baudcount <= 0;
			if(state == rx__data) begin
				if(bitcount < 3'd7)
					bitcount <= bitcount +1;
			end
	end
		else begin
			baudcount <= baudcount +1;
		end
	end
end

always@(posedge clk or posedge rst ) begin
        if(rst)
                parity <= 0;
        else if(state == rx__data && baudcount == t_bit-1 && bitcount == 3'd7)begin
                if(parity_en) begin
                        if(parity_type)
                                parity <= ~^{rx,shift_reg};
                        else
                                parity <= ^{rx,shift_reg};
                end
                else
                        parity <= 0;
        end
end

always@(posedge clk or posedge rst) begin
	if(rst) begin
		shift_reg <= 0;
	end
	else if(state == rx__data && baudcount == t_bit-1) begin
		shift_reg <= {rx,shift_reg[7:1]};
	end
end

always@(*) begin
	next = state;
	parity_error = 0;
	case(state)
		rx_idle : begin
			if(rx == 0)
				next = rx_start_check;
			else	
				next = rx_idle;
		end
		
		rx_start_check : begin
			if(baudcount == half_bit-1) begin
				if(rx == 0)
					next = rx__data;
				else 
					next = rx_idle;
			end
			else
				next = rx_start_check;
		end
		rx__data : begin
			if(baudcount == t_bit-1) begin
						if (bitcount == 3'd7) begin
                                if(parity_en)
                                     next = rx_parity;
                                else
									next = rx_stop;
						end
				else begin
					next = rx__data;
				end
			end
			else begin
				next = rx__data;
			end
		end

		rx_parity : begin
                        if(baudcount == t_bit-1) begin
                            if(rx != parity)
                                parity_error = 1;
                             else
                                parity_error = 0;
                               
                                
                                next = rx_stop;
                        end
                        else
                                next = rx_parity;
                end
		
		rx_stop: begin
    			if (baudcount == t_bit-1) begin
    			 if (rx == 1'b1) 
        			next = rx_idle;
        		else 
        			next = rx_stop;
    		    end
    		    else
    		      next = rx_stop;
		end
		default : begin 
			next = rx_idle;
		end
	endcase
end
always @(posedge clk or posedge rst) begin
    if (rst) begin
        rx_data  <= 8'd0;
        rx_valid <= 1'b0;
        rx_error <= 1'b0;
    end
    else begin
        if (state == rx_stop && baudcount == t_bit-1) begin
            if (rx == 1'b1) begin
                rx_data  <= shift_reg;
                rx_valid <= 1'b1;
                rx_error <= parity_error;
            end
            else begin
                rx_error <= 1'b1;
                rx_valid <= 1'b0;
            end
        end
    end
end
endmodule

uart_verify/uart_tx.v
module transmiter #(parameter integer clock = 50000000,baudrate = 115200)
(input clk,
input rst,
input tx_start,
input [7:0] tx_data,
input parity_en,
input parity_type,
output reg tx,
output reg tx_busy);

localparam integer t_bit = (clock/baudrate);

reg [2:0] state,next;
reg [12:0] baudcount;
reg [2:0] bitcount;
reg [7:0] shift_reg;
reg parity;

parameter tx_idle=3'd0,tx__start=3'd1,tx__data=3'd2,tx_parity=3'd3,tx_stop=3'd4;

always@(posedge clk or posedge rst) begin
if(rst)
state <= tx_idle;
else 
state <= next;
end

always @(posedge clk or posedge rst) begin

    if (rst) begin
        baudcount <= 0;
        bitcount  <= 0;
    end

    else if (state == tx_idle) begin
    	     baudcount <= 0;
    	     bitcount <=0;
	end
    else begin
          if (baudcount == t_bit-1) begin

            baudcount <= 0;
           
	  if(state == tx__data)begin
             if (bitcount < 3'd7)
                bitcount <= bitcount + 1;
	    end
	  end
	 else begin
                baudcount <= baudcount +1;
         end  
	end
    end

always@(posedge clk or posedge rst) begin
        if(rst)
                parity <= 0;
        else if(state == tx_idle && tx_start) begin
                if(parity_en) begin
                        if(parity_type)
                                parity <= ~^tx_data;
                        else
                                parity <= ^tx_data;
                end
                else
                        parity <= 0;
        end
end

always@(posedge clk or posedge rst ) begin
	if(rst)
		shift_reg <= 0;
	else begin
		if (state == tx_idle && tx_start)
    			shift_reg <= tx_data;
		else if (baudcount == t_bit-1 && state == tx__data)
    			shift_reg <= {1'b0,shift_reg[7:1]};
	end	
end

always@(*) begin
case(state)
tx_idle: begin
    tx = 1;
    tx_busy = 0;

    if (tx_start) begin
        next = tx__start;
    end
    else begin
        next = tx_idle;
    end
end

tx__start: begin
    tx = 0;
    tx_busy = 1;

    if (baudcount == t_bit-1) begin
        next = tx__data;
    end
    else begin
        next = tx__start;
    end
end

tx__data: begin

    tx = shift_reg[0];
    tx_busy = 1;

    if (baudcount == t_bit-1) begin
        if (bitcount == 4'd7) begin
            if (parity_en)
                next = tx_parity;
            else
                next = tx_stop;
        end
        else begin
            next = tx__data;
        end

    end
    else begin
        next = tx__data;
    end

end

tx_parity: begin
        tx = parity;
        tx_busy = 1;
        
        if(baudcount == t_bit-1)
                next = tx_stop;
        else
                next = tx_parity;
end

tx_stop: begin
		 tx = 1;
    	tx_busy = 1;

    if (baudcount == t_bit-1) begin
        next = tx_idle;
    end
    else begin
        next = tx_stop;
    end
end
	default : begin
		tx = 1;
		tx_busy = 0;
		next = tx_idle;
	end
 endcase
end

endmodule

uart_verify/uart_top.v
module uart #(parameter integer clock = 50000000,baudrate = 115200)
(input clk,
input rst,
input uart_rx,
output uart_tx,
//transmitter
input [7:0] tx_data,
input tx_start,
input parity_en,
input parity_type,
output tx_busy,
//receiver
output [7:0]rx_data,
output rx_valid,
output rx_error);

wire tx_internal;


transmiter #(.clock(clock),
	      .baudrate(baudrate))
uart_tx1(.clk(clk),
	 .rst(rst),
	 .tx_data(tx_data),
	 .tx_start(tx_start),
	 .parity_en(parity_en),
     .parity_type(parity_type),
	 .tx(tx_internal),
	 .tx_busy(tx_busy));
	
receiver #(.clock(clock),
	   .baudrate(baudrate))
uart_rx1(.clk(clk),
	 .rst(rst),
	 .rx(uart_rx),
     .parity_en(parity_en),
     .parity_type(parity_type),
	 .rx_data(rx_data),
	 .rx_valid(rx_valid),
	 .rx_error(rx_error));

assign uart_tx = tx_internal;

endmodule

uart_verify/uart_tb.v
module uart_tb;
reg clk;
reg rst;
wire uart_rx;
wire uart_tx;
//transmitter
reg [7:0] tx_data;
reg tx_start;
reg parity_en;
reg parity_type;
wire tx_busy;
//receiver
wire [7:0]rx_data;
wire rx_valid;
wire rx_error;

uart u1(.clk(clk),
	.rst(rst),
	.uart_tx(uart_tx),
	.uart_rx(uart_rx),
	.tx_data(tx_data),
	.tx_start(tx_start),
	.parity_en(parity_en),
    .parity_type(parity_type),
	.tx_busy(tx_busy),
	.rx_data(rx_data),
	.rx_valid(rx_valid),
	.rx_error(rx_error));
	
initial begin
	clk = 0;
	forever #10clk = ~clk;
end
assign uart_rx = uart_tx;

initial begin
	rst = 1; 
	tx_data = 8'h64; 
	tx_start = 0; 
	parity_en = 1;
	parity_type = 1;
	#100;
	
	rst = 0;
	#50;
	tx_start = 1; 
	#50; 
	tx_start = 0; 
	#50;
	#2000000;
	
    $finish;
end 


initial begin 
	        $monitor("time=%0t, parity_en=%0d, parity_type=%0d, tx_start=%0d, tx_data=%0d, tx_busy=%0d, uart_tx=%0d, uart_rx=%0d, rx_data=%0d, rx_valid=%0d, rx_error=%0d", $time, parity_en, parity_type, tx_start, tx_data, tx_busy, uart_tx, uart_rx, rx_data, rx_valid, rx_error);
end
initial begin
    $dumpfile("uart_wave.vcd");
    $dumpvars(0, uart_tb);
end

endmodule

uart_verify/uart_wave.vcd
$date
	Wed Sep  2 09:02:54 2026
$end
$version
	Icarus Verilog
$end
$timescale
	1s
$end
$scope module uart_tb $end
$var wire 1 ! uart_rx $end
$var wire 1 " uart_tx $end
$var wire 1 # tx_busy $end
$var wire 1 $ rx_valid $end
$var wire 1 % rx_error $end
$var wire 8 & rx_data [7:0] $end
$var reg 1 ' clk $end
$var reg 1 ( parity_en $end
$var reg 1 ) parity_type $end
$var reg 1 * rst $end
$var reg 8 + tx_data [7:0] $end
$var reg 1 , tx_start $end
$scope module u1 $end
$var wire 1 ' clk $end
$var wire 1 ( parity_en $end
$var wire 1 ) parity_type $end
$var wire 1 * rst $end
$var wire 8 - tx_data [7:0] $end
$var wire 1 , tx_start $end
$var wire 1 ! uart_rx $end
$var wire 1 " uart_tx $end
$var wire 1 . tx_internal $end
$var wire 1 # tx_busy $end
$var wire 1 $ rx_valid $end
$var wire 1 % rx_error $end
$var wire 8 / rx_data [7:0] $end
$var parameter 32 0 baudrate $end
$var parameter 32 1 clock $end
$scope module uart_rx1 $end
$var wire 1 ' clk $end
$var wire 1 ( parity_en $end
$var wire 1 ) parity_type $end
$var wire 1 * rst $end
$var wire 1 ! rx $end
$var parameter 32 2 baudrate $end
$var parameter 32 3 clock $end
$var parameter 32 4 half_bit $end
$var parameter 3 5 rx__data $end
$var parameter 3 6 rx_idle $end
$var parameter 3 7 rx_parity $end
$var parameter 3 8 rx_start_check $end
$var parameter 3 9 rx_stop $end
$var parameter 32 : t_bit $end
$var reg 13 ; baudcount [12:0] $end
$var reg 3 < bitcount [2:0] $end
$var reg 3 = next [2:0] $end
$var reg 1 > parity $end
$var reg 1 ? parity_error $end
$var reg 8 @ rx_data [7:0] $end
$var reg 1 % rx_error $end
$var reg 1 $ rx_valid $end
$var reg 8 A shift_reg [7:0] $end
$var reg 3 B state [2:0] $end
$upscope $end
$scope module uart_tx1 $end
$var wire 1 ' clk $end
$var wire 1 ( parity_en $end
$var wire 1 ) parity_type $end
$var wire 1 * rst $end
$var wire 8 C tx_data [7:0] $end
$var wire 1 , tx_start $end
$var parameter 32 D baudrate $end
$var parameter 32 E clock $end
$var parameter 32 F t_bit $end
$var parameter 3 G tx__data $end
$var parameter 3 H tx__start $end
$var parameter 3 I tx_idle $end
$var parameter 3 J tx_parity $end
$var parameter 3 K tx_stop $end
$var reg 13 L baudcount [12:0] $end
$var reg 3 M bitcount [2:0] $end
$var reg 3 N next [2:0] $end
$var reg 1 O parity $end
$var reg 8 P shift_reg [7:0] $end
$var reg 3 Q state [2:0] $end
$var reg 1 . tx $end
$var reg 1 # tx_busy $end
$upscope $end
$upscope $end
$upscope $end
$enddefinitions $end
$comment Show the parameter values. $end
$dumpall
b100 K
b11 J
b0 I
b1 H
b10 G
b110110010 F
b10111110101111000010000000 E
b11100001000000000 D
b110110010 :
b100 9
b101 8
b11 7
b0 6
b10 5
b11011001 4
b10111110101111000010000000 3
b11100001000000000 2
b10111110101111000010000000 1
b11100001000000000 0
$end
#0
$dumpvars
b0 Q
b0 P
0O
b0 N
b0 M
b0 L
b1100100 C
b0 B
b0 A
b0 @
0?
0>
b0 =
b0 <
b0 ;
b0 /
1.
b1100100 -
0,
b1100100 +
1*
1)
1(
0'
b0 &
0%
0$
0#
1"
1!
$end
#10
1'
#20
0'
#30
1'
#40
0'
#50
1'
#60
0'
#70
1'
#80
0'
#90
1'
#100
0'
0*
#110
1'
#120
0'
#130
1'
#140
0'
#150
b101 =
1#
0!
0"
0.
b1 Q
b1100100 P
b1 N
1'
1,
#160
0'
#170
b101 B
b1 L
1'
#180
0'
#190
b10 L
b1 ;
1'
#200
0'
0,
#210
b10 ;
b11 L
1'
#220
0'
#230
b100 L
b11 ;
1'
#240
0'
#250
b100 ;
b101 L
1'
#260
0'
#270
b110 L
b101 ;
1'
#280
0'
#290
b110 ;
b111 L
1'
#300
0'
#310
b1000 L
b111 ;
1'
#320
0'
#330
b1000 ;
b1001 L
1'
#340
0'
#350
b1010 L
b1001 ;
1'
#360
0'
#370
b1010 ;
b1011 L
1'
#380
0'
#390
b1100 L
b1011 ;
1'
#400
0'
#410
b1100 ;
b1101 L
1'
#420
0'
#430
b1110 L
b1101 ;
1'
#440
0'
#450
b1110 ;
b1111 L
1'
#460
0'
#470
b10000 L
b1111 ;
1'
#480
0'
#490
b10000 ;
b10001 L
1'
#500
0'
#510
b10010 L
b10001 ;
1'
#520
0'
#530
b10010 ;
b10011 L
1'
#540
0'
#550
b10100 L
b10011 ;
1'
#560
0'
#570
b10100 ;
b10101 L
1'
#580
0'
#590
b10110 L
b10101 ;
1'
#600
0'
#610
b10110 ;
b10111 L
1'
#620
0'
#630
b11000 L
b10111 ;
1'
#640
0'
#650
b11000 ;
b11001 L
1'
#660
0'
#670
b11010 L
b11001 ;
1'
#680
0'
#690
b11010 ;
b11011 L
1'
#700
0'
#710
b11100 L
b11011 ;
1'
#720
0'
#730
b11100 ;
b11101 L
1'
#740
0'
#750
b11110 L
b11101 ;
1'
#760
0'
#770
b11110 ;
b11111 L
1'
#780
0'
#790
b100000 L
b11111 ;
1'
#800
0'
#810
b100000 ;
b100001 L
1'
#820
0'
#830
b100010 L
b100001 ;
1'
#840
0'
#850
b100010 ;
b100011 L
1'
#860
0'
#870
b100100 L
b100011 ;
1'
#880
0'
#890
b100100 ;
b100101 L
1'
#900
0'
#910
b100110 L
b100101 ;
1'
#920
0'
#930
b100110 ;
b100111 L
1'
#940
0'
#950
b101000 L
b100111 ;
1'
#960
0'
#970
b101000 ;
b101001 L
1'
#980
0'
#990
b101010 L
b101001 ;
1'
#1000
0'
#1010
b101010 ;
b101011 L
1'
#1020
0'
#1030
b101100 L
b101011 ;
1'
#1040
0'
#1050
b101100 ;
b101101 L
1'
#1060
0'
#1070
b101110 L
b101101 ;
1'
#1080
0'
#1090
b101110 ;
b101111 L
1'
#1100
0'
#1110
b110000 L
b101111 ;
1'
#1120
0'
#1130
b110000 ;
b110001 L
1'
#1140
0'
#1150
b110010 L
b110001 ;
1'
#1160
0'
#1170
b110010 ;
b110011 L
1'
#1180
0'
#1190
b110100 L
b110011 ;
1'
#1200
0'
#1210
b110100 ;
b110101 L
1'
#1220
0'
#1230
b110110 L
b110101 ;
1'
#1240
0'
#1250
b110110 ;
b110111 L
1'
#1260
0'
#1270
b111000 L
b110111 ;
1'
#1280
0'
#1290
b111000 ;
b111001 L
1'
#1300
0'
#1310
b111010 L
b111001 ;
1'
#1320
0'
#1330
b111010 ;
b111011 L
1'
#1340
0'
#1350
b111100 L
b111011 ;
1'
#1360
0'
#1370
b111100 ;
b111101 L
1'
#1380
0'
#1390
b111110 L
b111101 ;
1'
#1400
0'
#1410
b111110 ;
b111111 L
1'
#1420
0'
#1430
b1000000 L
b111111 ;
1'
#1440
0'
#1450
b1000000 ;
b1000001 L
1'
#1460
0'
#1470
b1000010 L
b1000001 ;
1'
#1480
0'
#1490
b1000010 ;
b1000011 L
1'
#1500
0'
#1510
b1000100 L
b1000011 ;
1'
#1520
0'
#1530
b1000100 ;
b1000101 L
1'
#1540
0'
#1550
b1000110 L
b1000101 ;
1'
#1560
0'
#1570
b1000110 ;
b1000111 L
1'
#1580
0'
#1590
b1001000 L
b1000111 ;
1'
#1600
0'
#1610
b1001000 ;
b1001001 L
1'
#1620
0'
#1630
b1001010 L
b1001001 ;
1'
#1640
0'
#1650
b1001010 ;
b1001011 L
1'
#1660
0'
#1670
b1001100 L
b1001011 ;
1'
#1680
0'
#1690
b1001100 ;
b1001101 L
1'
#1700
0'
#1710
b1001110 L
b1001101 ;
1'
#1720
0'
#1730
b1001110 ;
b1001111 L
1'
#1740
0'
#1750
b1010000 L
b1001111 ;
1'
#1760
0'
#1770
b1010000 ;
b1010001 L
1'
#1780
0'
#1790
b1010010 L
b1010001 ;
1'
#1800
0'
#1810
b1010010 ;
b1010011 L
1'
#1820
0'
#1830
b1010100 L
b1010011 ;
1'
#1840
0'
#1850
b1010100 ;
b1010101 L
1'
#1860
0'
#1870
b1010110 L
b1010101 ;
1'
#1880
0'
#1890
b1010110 ;
b1010111 L
1'
#1900
0'
#1910
b1011000 L
b1010111 ;
1'
#1920
0'
#1930
b1011000 ;
b1011001 L
1'
#1940
0'
#1950
b1011010 L
b1011001 ;
1'
#1960
0'
#1970
b1011010 ;
b1011011 L
1'
#1980
0'
#1990
b1011100 L
b1011011 ;
1'
#2000
0'
#2010
b1011100 ;
b1011101 L
1'
#2020
0'
#2030
b1011110 L
b1011101 ;
1'
#2040
0'
#2050
b1011110 ;
b1011111 L
1'
#2060
0'
#2070
b1100000 L
b1011111 ;
1'
#2080
0'
#2090
b1100000 ;
b1100001 L
1'
#2100
0'
#2110
b1100010 L
b1100001 ;
1'
#2120
0'
#2130
b1100010 ;
b1100011 L
1'
#2140
0'
#2150
b1100100 L
b1100011 ;
1'
#2160
0'
#2170
b1100100 ;
b1100101 L
1'
#2180
0'
#2190
b1100110 L
b1100101 ;
1'
#2200
0'
#2210
b1100110 ;
b1100111 L
1'
#2220
0'
#2230
b1101000 L
b1100111 ;
1'
#2240
0'
#2250
b1101000 ;
b1101001 L
1'
#2260
0'
#2270
b1101010 L
b1101001 ;
1'
#2280
0'
#2290
b1101010 ;
b1101011 L
1'
#2300
0'
#2310
b1101100 L
b1101011 ;
1'
#2320
0'
#2330
b1101100 ;
b1101101 L
1'
#2340
0'
#2350
b1101110 L
b1101101 ;
1'
#2360
0'
#2370
b1101110 ;
b1101111 L
1'
#2380
0'
#2390
b1110000 L
b1101111 ;
1'
#2400
0'
#2410
b1110000 ;
b1110001 L
1'
#2420
0'
#2430
b1110010 L
b1110001 ;
1'
#2440
0'
#2450
b1110010 ;
b1110011 L
1'
#2460
0'
#2470
b1110100 L
b1110011 ;
1'
#2480
0'
#2490
b1110100 ;
b1110101 L
1'
#2500
0'
#2510
b1110110 L
b1110101 ;
1'
#2520
0'
#2530
b1110110 ;
b1110111 L
1'
#2540
0'
#2550
b1111000 L
b1110111 ;
1'
#2560
0'
#2570
b1111000 ;
b1111001 L
1'
#2580
0'
#2590
b1111010 L
b1111001 ;
1'
#2600
0'
#2610
b1111010 ;
b1111011 L
1'
#2620
0'
#2630
b1111100 L
b1111011 ;
1'
#2640
0'
#2650
b1111100 ;
b1111101 L
1'
#2660
0'
#2670
b1111110 L
b1111101 ;
1'
#2680
0'
#2690
b1111110 ;
b1111111 L
1'
#2700
0'
#2710
b10000000 L
b1111111 ;
1'
#2720
0'
#2730
b10000000 ;
b10000001 L
1'
#2740
0'
#2750
b10000010 L
b10000001 ;
1'
#2760
0'
#2770
b10000010 ;
b10000011 L
1'
#2780
0'
#2790
b10000100 L
b10000011 ;
1'
#2800
0'
#2810
b10000100 ;
b10000101 L
1'
#2820
0'
#2830
b10000110 L
b10000101 ;
1'
#2840
0'
#2850
b10000110 ;
b10000111 L
1'
#2860
0'
#2870
b10001000 L
b10000111 ;
1'
#2880
0'
#2890
b10001000 ;
b10001001 L
1'
#2900
0'
#2910
b10001010 L
b10001001 ;
1'
#2920
0'
#2930
b10001010 ;
b10001011 L
1'
#2940
0'
#2950
b10001100 L
b10001011 ;
1'
#2960
0'
#2970
b10001100 ;
b10001101 L
1'
#2980
0'
#2990
b10001110 L
b10001101 ;
1'
#3000
0'
#3010
b10001110 ;
b10001111 L
1'
#3020
0'
#3030
b10010000 L
b10001111 ;
1'
#3040
0'
#3050
b10010000 ;
b10010001 L
1'
#3060
0'
#3070
b10010010 L
b10010001 ;
1'
#3080
0'
#3090
b10010010 ;
b10010011 L
1'
#3100
0'
#3110
b10010100 L
b10010011 ;
1'
#3120
0'
#3130
b10010100 ;
b10010101 L
1'
#3140
0'
#3150
b10010110 L
b10010101 ;
1'
#3160
0'
#3170
b10010110 ;
b10010111 L
1'
#3180
0'
#3190
b10011000 L
b10010111 ;
1'
#3200
0'
#3210
b10011000 ;
b10011001 L
1'
#3220
0'
#3230
b10011010 L
b10011001 ;
1'
#3240
0'
#3250
b10011010 ;
b10011011 L
1'
#3260
0'
#3270
b10011100 L
b10011011 ;
1'
#3280
0'
#3290
b10011100 ;
b10011101 L
1'
#3300
0'
#3310
b10011110 L
b10011101 ;
1'
#3320
0'
#3330
b10011110 ;
b10011111 L
1'
#3340
0'
#3350
b10100000 L
b10011111 ;
1'
#3360
0'
#3370
b10100000 ;
b10100001 L
1'
#3380
0'
#3390
b10100010 L
b10100001 ;
1'
#3400
0'
#3410
b10100010 ;
b10100011 L
1'
#3420
0'
#3430
b10100100 L
b10100011 ;
1'
#3440
0'
#3450
b10100100 ;
b10100101 L
1'
#3460
0'
#3470
b10100110 L
b10100101 ;
1'
#3480
0'
#3490
b10100110 ;
b10100111 L
1'
#3500
0'
#3510
b10101000 L
b10100111 ;
1'
#3520
0'
#3530
b10101000 ;
b10101001 L
1'
#3540
0'
#3550
b10101010 L
b10101001 ;
1'
#3560
0'
#3570
b10101010 ;
b10101011 L
1'
#3580
0'
#3590
b10101100 L
b10101011 ;
1'
#3600
0'
#3610
b10101100 ;
b10101101 L
1'
#3620
0'
#3630
b10101110 L
b10101101 ;
1'
#3640
0'
#3650
b10101110 ;
b10101111 L
1'
#3660
0'
#3670
b10110000 L
b10101111 ;
1'
#3680
0'
#3690
b10110000 ;
b10110001 L
1'
#3700
0'
#3710
b10110010 L
b10110001 ;
1'
#3720
0'
#3730
b10110010 ;
b10110011 L
1'
#3740
0'
#3750
b10110100 L
b10110011 ;
1'
#3760
0'
#3770
b10110100 ;
b10110101 L
1'
#3780
0'
#3790
b10110110 L
b10110101 ;
1'
#3800
0'
#3810
b10110110 ;
b10110111 L
1'
#3820
0'
#3830
b10111000 L
b10110111 ;
1'
#3840
0'
#3850
b10111000 ;
b10111001 L
1'
#3860
0'
#3870
b10111010 L
b10111001 ;
1'
#3880
0'
#3890
b10111010 ;
b10111011 L
1'
#3900
0'
#3910
b10111100 L
b10111011 ;
1'
#3920
0'
#3930
b10111100 ;
b10111101 L
1'
#3940
0'
#3950
b10111110 L
b10111101 ;
1'
#3960
0'
#3970
b10111110 ;
b10111111 L
1'
#3980
0'
#3990
b11000000 L
b10111111 ;
1'
#4000
0'
#4010
b11000000 ;
b11000001 L
1'
#4020
0'
#4030
b11000010 L
b11000001 ;
1'
#4040
0'
#4050
b11000010 ;
b11000011 L
1'
#4060
0'
#4070
b11000100 L
b11000011 ;
1'
#4080
0'
#4090
b11000100 ;
b11000101 L
1'
#4100
0'
#4110
b11000110 L
b11000101 ;
1'
#4120
0'
#4130
b11000110 ;
b11000111 L
1'
#4140
0'
#4150
b11001000 L
b11000111 ;
1'
#4160
0'
#4170
b11001000 ;
b11001001 L
1'
#4180
0'
#4190
b11001010 L
b11001001 ;
1'
#4200
0'
#4210
b11001010 ;
b11001011 L
1'
#4220
0'
#4230
b11001100 L
b11001011 ;
1'
#4240
0'
#4250
b11001100 ;
b11001101 L
1'
#4260
0'
#4270
b11001110 L
b11001101 ;
1'
#4280
0'
#4290
b11001110 ;
b11001111 L
1'
#4300
0'
#4310
b11010000 L
b11001111 ;
1'
#4320
0'
#4330
b11010000 ;
b11010001 L
1'
#4340
0'
#4350
b11010010 L
b11010001 ;
1'
#4360
0'
#4370
b11010010 ;
b11010011 L
1'
#4380
0'
#4390
b11010100 L
b11010011 ;
1'
#4400
0'
#4410
b11010100 ;
b11010101 L
1'
#4420
0'
#4430
b11010110 L
b11010101 ;
1'
#4440
0'
#4450
b11010110 ;
b11010111 L
1'
#4460
0'
#4470
b11011000 L
b11010111 ;
1'
#4480
0'
#4490
b10 =
b11011000 ;
b11011001 L
1'
#4500
0'
#4510
b11011010 L
b10 B
b0 ;
1'
#4520
0'
#4530
b1 ;
b11011011 L
1'
#4540
0'
#4550
b11011100 L
b10 ;
1'
#4560
0'
#4570
b11 ;
b11011101 L
1'
#4580
0'
#4590
b11011110 L
b100 ;
1'
#4600
0'
#4610
b101 ;
b11011111 L
1'
#4620
0'
#4630
b11100000 L
b110 ;
1'
#4640
0'
#4650
b111 ;
b11100001 L
1'
#4660
0'
#4670
b11100010 L
b1000 ;
1'
#4680
0'
#4690
b1001 ;
b11100011 L
1'
#4700
0'
#4710
b11100100 L
b1010 ;
1'
#4720
0'
#4730
b1011 ;
b11100101 L
1'
#4740
0'
#4750
b11100110 L
b1100 ;
1'
#4760
0'
#4770
b1101 ;
b11100111 L
1'
#4780
0'
#4790
b11101000 L
b1110 ;
1'
#4800
0'
#4810
b1111 ;
b11101001 L
1'
#4820
0'
#4830
b11101010 L
b10000 ;
1'
#4840
0'
#4850
b10001 ;
b11101011 L
1'
#4860
0'
#4870
b11101100 L
b10010 ;
1'
#4880
0'
#4890
b10011 ;
b11101101 L
1'
#4900
0'
#4910
b11101110 L
b10100 ;
1'
#4920
0'
#4930
b10101 ;
b11101111 L
1'
#4940
0'
#4950
b11110000 L
b10110 ;
1'
#4960
0'
#4970
b10111 ;
b11110001 L
1'
#4980
0'
#4990
b11110010 L
b11000 ;
1'
#5000
0'
#5010
b11001 ;
b11110011 L
1'
#5020
0'
#5030
b11110100 L
b11010 ;
1'
#5040
0'
#5050
b11011 ;
b11110101 L
1'
#5060
0'
#5070
b11110110 L
b11100 ;
1'
#5080
0'
#5090
b11101 ;
b11110111 L
1'
#5100
0'
#5110
b11111000 L
b11110 ;
1'
#5120
0'
#5130
b11111 ;
b11111001 L
1'
#5140
0'
#5150
b11111010 L
b100000 ;
1'
#5160
0'
#5170
b100001 ;
b11111011 L
1'
#5180
0'
#5190
b11111100 L
b100010 ;
1'
#5200
0'
#5210
b100011 ;
b11111101 L
1'
#5220
0'
#5230
b11111110 L
b100100 ;
1'
#5240
0'
#5250
b100101 ;
b11111111 L
1'
#5260
0'
#5270
b100000000 L
b100110 ;
1'
#5280
0'
#5290
b100111 ;
b100000001 L
1'
#5300
0'
#5310
b100000010 L
b101000 ;
1'
#5320
0'
#5330
b101001 ;
b100000011 L
1'
#5340
0'
#5350
b100000100 L
b101010 ;
1'
#5360
0'
#5370
b101011 ;
b100000101 L
1'
#5380
0'
#5390
b100000110 L
b101100 ;
1'
#5400
0'
#5410
b101101 ;
b100000111 L
1'
#5420
0'
#5430
b100001000 L
b101110 ;
1'
#5440
0'
#5450
b101111 ;
b100001001 L
1'
#5460
0'
#5470
b100001010 L
b110000 ;
1'
#5480
0'
#5490
b110001 ;
b100001011 L
1'
#5500
0'
#5510
b100001100 L
b110010 ;
1'
#5520
0'
#5530
b110011 ;
b100001101 L
1'
#5540
0'
#5550
b100001110 L
b110100 ;
1'
#5560
0'
#5570
b110101 ;
b100001111 L
1'
#5580
0'
#5590
b100010000 L
b110110 ;
1'
#5600
0'
#5610
b110111 ;
b100010001 L
1'
#5620
0'
#5630
b100010010 L
b111000 ;
1'
#5640
0'
#5650
b111001 ;
b100010011 L
1'
#5660
0'
#5670
b100010100 L
b111010 ;
1'
#5680
0'
#5690
b111011 ;
b100010101 L
1'
#5700
0'
#5710
b100010110 L
b111100 ;
1'
#5720
0'
#5730
b111101 ;
b100010111 L
1'
#5740
0'
#5750
b100011000 L
b111110 ;
1'
#5760
0'
#5770
b111111 ;
b100011001 L
1'
#5780
0'
#5790
b100011010 L
b1000000 ;
1'
#5800
0'
#5810
b1000001 ;
b100011011 L
1'
#5820
0'
#5830
b100011100 L
b1000010 ;
1'
#5840
0'
#5850
b1000011 ;
b100011101 L
1'
#5860
0'
#5870
b100011110 L
b1000100 ;
1'
#5880
0'
#5890
b1000101 ;
b100011111 L
1'
#5900
0'
#5910
b100100000 L
b1000110 ;
1'
#5920
0'
#5930
b1000111 ;
b100100001 L
1'
#5940
0'
#5950
b100100010 L
b1001000 ;
1'
#5960
0'
#5970
b1001001 ;
b100100011 L
1'
#5980
0'
#5990
b100100100 L
b1001010 ;
1'
#6000
0'
#6010
b1001011 ;
b100100101 L
1'
#6020
0'
#6030
b100100110 L
b1001100 ;
1'
#6040
0'
#6050
b1001101 ;
b100100111 L
1'
#6060
0'
#6070
b100101000 L
b1001110 ;
1'
#6080
0'
#6090
b1001111 ;
b100101001 L
1'
#6100
0'
#6110
b100101010 L
b1010000 ;
1'
#6120
0'
#6130
b1010001 ;
b100101011 L
1'
#6140
0'
#6150
b100101100 L
b1010010 ;
1'
#6160
0'
#6170
b1010011 ;
b100101101 L
1'
#6180
0'
#6190
b100101110 L
b1010100 ;
1'
#6200
0'
#6210
b1010101 ;
b100101111 L
1'
#6220
0'
#6230
b100110000 L
b1010110 ;
1'
#6240
0'
#6250
b1010111 ;
b100110001 L
1'
#6260
0'
#6270
b100110010 L
b1011000 ;
1'
#6280
0'
#6290
b1011001 ;
b100110011 L
1'
#6300
0'
#6310
b100110100 L
b1011010 ;
1'
#6320
0'
#6330
b1011011 ;
b100110101 L
1'
#6340
0'
#6350
b100110110 L
b1011100 ;
1'
#6360
0'
#6370
b1011101 ;
b100110111 L
1'
#6380
0'
#6390
b100111000 L
b1011110 ;
1'
#6400
0'
#6410
b1011111 ;
b100111001 L
1'
#6420
0'
#6430
b100111010 L
b1100000 ;
1'
#6440
0'
#6450
b1100001 ;
b100111011 L
1'
#6460
0'
#6470
b100111100 L
b1100010 ;
1'
#6480
0'
#6490
b1100011 ;
b100111101 L
1'
#6500
0'
#6510
b100111110 L
b1100100 ;
1'
#6520
0'
#6530
b1100101 ;
b100111111 L
1'
#6540
0'
#6550
b101000000 L
b1100110 ;
1'
#6560
0'
#6570
b1100111 ;
b101000001 L
1'
#6580
0'
#6590
b101000010 L
b1101000 ;
1'
#6600
0'
#6610
b1101001 ;
b101000011 L
1'
#6620
0'
#6630
b101000100 L
b1101010 ;
1'
#6640
0'
#6650
b1101011 ;
b101000101 L
1'
#6660
0'
#6670
b101000110 L
b1101100 ;
1'
#6680
0'
#6690
b1101101 ;
b101000111 L
1'
#6700
0'
