SPI/spi_slave.v
module spi_slave (
    input        reset,
    input        cs,
    input        sclk,
    input        mosi,
    input  [7:0] tx_data,

    output       miso,
    output reg [7:0] rx_data,
    output reg   done
);

reg [7:0] rx_shift;
reg [3:0] rx_count;

reg [3:0] tx_count;


/* RECEIVE MOSI */

always @(posedge sclk or posedge reset) begin

    if (reset) begin
        rx_shift <= 8'h00;
        rx_data  <= 8'h00;
        rx_count <= 4'd0;
        done     <= 1'b0;
    end

    else if (!cs) begin

        rx_shift <= {rx_shift[6:0], mosi};

        if (rx_count == 4'd7) begin

            rx_data <= {rx_shift[6:0], mosi};
            rx_count <= 4'd0;
            done <= 1'b1;

        end

        else begin

            rx_count <= rx_count + 1'b1;
            done <= 1'b0;

        end
    end

    else begin
        done <= 1'b0;
    end

end


/* TRANSMIT COUNTER */

always @(negedge sclk or posedge reset) begin

    if (reset) begin
        tx_count <= 4'd0;
    end

    else if (!cs) begin

        if (tx_count == 4'd7)
            tx_count <= 4'd0;
        else
            tx_count <= tx_count + 1'b1;

    end

    else begin
        tx_count <= 4'd0;
    end

end


/* MISO */

assign miso = (!cs) ? tx_data[7 - tx_count] : 1'b0;

endmodule

SPI/spi_master.v
module spi_master (
    input        clk,
    input        reset,
    input        start,
    input  [7:0] tx_data,
    input        miso,

    output reg   sclk,
    output reg   mosi,
    output reg   cs,
    output reg [7:0] rx_data,
    output reg   busy,
    output reg   done
);

reg [7:0] tx_shift;
reg [7:0] rx_shift;
reg [3:0] bit_count;

always @(posedge clk or posedge reset) begin

    if (reset) begin
        sclk     <= 1'b0;
        mosi     <= 1'b0;
        cs       <= 1'b1;
        rx_data  <= 8'b0;
        tx_shift <= 8'b0;
        rx_shift <= 8'b0;
        bit_count <= 4'd0;
        busy     <= 1'b0;
        done     <= 1'b0;
    end

    else begin
        done <= 1'b0;

        if (!busy) begin

            if (start) begin
                busy      <= 1'b1;
                cs        <= 1'b0;
                sclk      <= 1'b0;

                tx_shift  <= tx_data;
                rx_shift  <= 8'b0;
                bit_count <= 4'd0;

                mosi      <= tx_data[7];
            end
        end

        else begin

            if (sclk == 1'b0) begin
                sclk <= 1'b1;

                rx_shift <= {rx_shift[6:0], miso};

            end

            else begin
                sclk <= 1'b0;

                if (bit_count == 4'd7) begin

                    busy <= 1'b0;
                    cs   <= 1'b1;
                    done <= 1'b1;

                    rx_data <= {rx_shift[6:0], miso};
                    mosi <= 1'b0;

                end

                else begin
                    bit_count <= bit_count + 1'b1;

                    tx_shift <= {tx_shift[6:0], 1'b0};
                    mosi <= tx_shift[6];
                end
            end
        end
    end
end

endmodule

SPI/spi_top.v
module spi_top (
    input        clk,
    input        reset,
    input        start,

    input  [7:0]  master_tx_data,
    input  [7:0]  slave_tx_data,

    output [7:0]  master_rx_data,
    output [7:0]  slave_rx_data,

    output        master_busy,
    output        master_done,
    output        slave_done
);

wire sclk;
wire mosi;
wire miso;
wire cs;


spi_master u_master (
    .clk       (clk),
    .reset     (reset),
    .start     (start),
    .tx_data   (master_tx_data),
    .miso      (miso),

    .sclk      (sclk),
    .mosi      (mosi),
    .cs        (cs),
    .rx_data   (master_rx_data),
    .busy      (master_busy),
    .done      (master_done)
);


spi_slave u_slave (
    .reset     (reset),
    .cs        (cs),
    .sclk      (sclk),
    .mosi      (mosi),
    .tx_data   (slave_tx_data),

    .miso      (miso),
    .rx_data   (slave_rx_data),
    .done       (slave_done)
);

endmodule

SPI/spi_tb.v
`timescale 1ns/1ps

module spi_tb;

reg clk;
reg reset;
reg start;

reg [7:0] master_tx_data;
reg [7:0] slave_tx_data;

wire [7:0] master_rx_data;
wire [7:0] slave_rx_data;

wire master_busy;
wire master_done;
wire slave_done;


spi_top uut (
    .clk            (clk),
    .reset          (reset),
    .start          (start),
    .master_tx_data (master_tx_data),
    .slave_tx_data  (slave_tx_data),
    .master_rx_data (master_rx_data),
    .slave_rx_data  (slave_rx_data),
    .master_busy    (master_busy),
    .master_done    (master_done),
    .slave_done     (slave_done)
);


always #5 clk = ~clk;


initial begin

    clk = 0;
    reset = 1;
    start = 0;
    master_tx_data = 8'h00;
    slave_tx_data = 8'h00;

    #20;

    reset = 0;

    master_tx_data = 8'hA5;
    slave_tx_data  = 8'h3C;

    #10;

    start = 1;

    #10;

    start = 0;

    wait(master_done);

    #20;

    $display("--------------------------------");
    $display("SPI TRANSFER");
    $display("--------------------------------");
    $display("MASTER TX = %h", master_tx_data);
    $display("SLAVE  TX = %h", slave_tx_data);
    $display("MASTER RX = %h", master_rx_data);
    $display("SLAVE  RX = %h", slave_rx_data);
    $display("--------------------------------");


    if (master_rx_data == slave_tx_data)
        $display("MASTER RECEIVE PASS");
    else
        $display("MASTER RECEIVE FAIL");


    if (slave_rx_data == master_tx_data)
        $display("SLAVE RECEIVE PASS");
    else
        $display("SLAVE RECEIVE FAIL");

    $display("--------------------------------");

    #20;

    $finish;

end


initial begin
    $dumpfile("spi.vcd");
    $dumpvars(0, spi_tb);
end

endmodule

SPI/spi.vcd
$date
	Mon Sep  7 12:49:00 2026
$end
$version
	Icarus Verilog
$end
$timescale
	1ps
$end
$scope module spi_tb $end
$var wire 8 ! slave_rx_data [7:0] $end
$var wire 1 " slave_done $end
$var wire 8 # master_rx_data [7:0] $end
$var wire 1 $ master_done $end
$var wire 1 % master_busy $end
$var reg 1 & clk $end
$var reg 8 ' master_tx_data [7:0] $end
$var reg 1 ( reset $end
$var reg 8 ) slave_tx_data [7:0] $end
$var reg 1 * start $end
$scope module uut $end
$var wire 1 & clk $end
$var wire 8 + master_tx_data [7:0] $end
$var wire 1 ( reset $end
$var wire 8 , slave_tx_data [7:0] $end
$var wire 1 * start $end
$var wire 8 - slave_rx_data [7:0] $end
$var wire 1 " slave_done $end
$var wire 1 . sclk $end
$var wire 1 / mosi $end
$var wire 1 0 miso $end
$var wire 8 1 master_rx_data [7:0] $end
$var wire 1 $ master_done $end
$var wire 1 % master_busy $end
$var wire 1 2 cs $end
$scope module u_master $end
$var wire 1 & clk $end
$var wire 1 ( reset $end
$var wire 1 * start $end
$var wire 8 3 tx_data [7:0] $end
$var wire 1 0 miso $end
$var reg 4 4 bit_count [3:0] $end
$var reg 1 % busy $end
$var reg 1 2 cs $end
$var reg 1 $ done $end
$var reg 1 / mosi $end
$var reg 8 5 rx_data [7:0] $end
$var reg 8 6 rx_shift [7:0] $end
$var reg 1 . sclk $end
$var reg 8 7 tx_shift [7:0] $end
$upscope $end
$scope module u_slave $end
$var wire 1 2 cs $end
$var wire 1 / mosi $end
$var wire 1 ( reset $end
$var wire 1 . sclk $end
$var wire 8 8 tx_data [7:0] $end
$var wire 1 0 miso $end
$var reg 1 " done $end
$var reg 4 9 rx_count [3:0] $end
$var reg 8 : rx_data [7:0] $end
$var reg 8 ; rx_shift [7:0] $end
$var reg 4 < tx_count [3:0] $end
$upscope $end
$upscope $end
$upscope $end
$enddefinitions $end
$comment Show the parameter values. $end
$dumpall
$end
#0
$dumpvars
b0 <
b0 ;
b0 :
b0 9
b0 8
b0 7
b0 6
b0 5
b0 4
b0 3
12
b0 1
00
0/
0.
b0 -
b0 ,
b0 +
0*
b0 )
1(
b0 '
0&
0%
0$
b0 #
0"
b0 !
$end
#5000
1&
#10000
0&
#15000
1&
#20000
0&
b111100 )
b111100 ,
b111100 8
b10100101 '
b10100101 +
b10100101 3
0(
#25000
1&
#30000
0&
1*
#35000
1/
b10100101 7
02
1%
1&
#40000
0&
0*
#45000
b1 9
b1 ;
1.
1&
#50000
0&
#55000
b1 <
0/
b1001010 7
b1 4
0.
1&
#60000
0&
#65000
b10 9
b10 ;
1.
1&
#70000
0&
#75000
10
b10 <
1/
b10010100 7
b10 4
0.
1&
#80000
0&
#85000
b11 9
b101 ;
b1 6
1.
1&
#90000
0&
#95000
b11 <
0/
b101000 7
b11 4
0.
1&
#100000
0&
#105000
b100 9
b1010 ;
b11 6
1.
1&
#110000
0&
#115000
b100 <
b1010000 7
b100 4
0.
1&
#120000
0&
#125000
b101 9
b10100 ;
b111 6
1.
1&
#130000
0&
#135000
b101 <
1/
b10100000 7
b101 4
0.
1&
#140000
0&
#145000
b110 9
b101001 ;
b1111 6
1.
1&
#150000
0&
#155000
00
b110 <
0/
b1000000 7
b110 4
0.
1&
#160000
0&
#165000
b111 9
b1010010 ;
b11110 6
1.
1&
#170000
0&
#175000
b111 <
1/
b10000000 7
b111 4
0.
1&
#180000
0&
#185000
1"
b0 9
b10100101 !
b10100101 -
b10100101 :
b10100101 ;
b111100 6
1.
1&
#190000
0&
#195000
b0 <
0/
b1111000 #
b1111000 1
b1111000 5
1$
12
0%
0.
1&
#200000
0&
#205000
0$
1&
